{
    "meta": {
        "symbol": "BTA",
        "name": "Bata",
        "supply": {
            "max": "10000000"
        },
        "web": {
            "websites": [
                "http:\/\/www.bata.io\/"
            ],
            "announcement": "https:\/\/bitcointalk.org\/index.php?topic=2297895.0",
            "source_code": "https:\/\/github.com\/BTA-BATA\/BATA-SOURCE",
            "explorers": [
                "https:\/\/chainz.cryptoid.info\/bta\/",
                "http:\/\/bata.midnightminer.net\/"
            ],
            "coinmarketcap": "https:\/\/coinmarketcap.com\/currencies\/bata\/",
            "message_board": [
                "https:\/\/medium.com\/@bata.io"
            ],
            "chat": [
                "https:\/\/t.me\/batacurrency",
                "https:\/\/discordapp.com\/invite\/SM8jQTQ"
            ]
        },
        "original_codebase": "bitcoin"
    },
    "main": {
        "symbol": "BTA",
        "name": "Bata - Mainnet",
        "testnet": false,
        "port": 5784,
        "port_rpc": 5493,
        "protocol": {
            "magic": "0x34c3afeb"
        },
        "seeds_dns": [
            "list.batadnsseed.bata.io",
            "batadnsseed.midnightminer.net"
        ],
        "prefixes": {
            "private": 188,
            "public": 25,
            "scripthash": 5,
            "bech32": null,
            "bip44": 89,
            "extended": {
                "xpub": {
                    "public": "0xa40c86fa",
                    "private": "0xa40b91bd"
                },
                "ypub": {
                    "public": "0x049d7cb2",
                    "private": "0x049d7878",
                    "undefined_used_btc": true
                },
                "zpub": {
                    "public": "0x04b24746",
                    "private": "0x04b2430c",
                    "undefined_used_btc": true
                },
                "Ypub": {
                    "public": "0x0295b43f",
                    "private": "0x0295b005",
                    "undefined_used_btc": true
                },
                "Zpub": {
                    "public": "0x02aa7ed3",
                    "private": "0x02aa7a99",
                    "undefined_used_btc": true
                }
            }
        },
        "hash_genesis_block": "b4bee36fd54a6176fd832f462641415c142d50e4b378f71c041870c2b1186bc8",
        "message_magic": "\u0015Bata Signed Message:\n",
        "decimals": 8
    },
    "test": {
        "symbol": "BTA",
        "name": "Bata - Testnet",
        "testnet": true,
        "port": 33813,
        "port_rpc": 33812,
        "protocol": {
            "magic": "0xbaadafc5"
        },
        "seeds_dns": [
            "testnet-seed.bata.io",
            "testnet-bata.midnightminer.net",
            "dnsseed.wemine-testnet.com"
        ],
        "prefixes": {
            "private": 239,
            "public": 111,
            "scripthash": 196,
            "bech32": null,
            "bip44": 1,
            "extended": {
                "xpub": {
                    "public": "0x043587cf",
                    "private": "0x04358394"
                },
                "ypub": {
                    "public": "0x044a5262",
                    "private": "0x044a4e28",
                    "undefined_used_btc": true
                },
                "zpub": {
                    "public": "0x045f1cf6",
                    "private": "0x045f18bc",
                    "undefined_used_btc": true
                },
                "Zpub": {
                    "public": "0x02575483",
                    "private": "0x02575048",
                    "undefined_used_btc": true
                }
            }
        },
        "hash_genesis_block": "00000a6800e5e2b43515cd12da56861eb482ebcdfa6ee92c1a8d7836ff654500",
        "message_magic": "\u0015Bata Signed Message:\n",
        "decimals": 8
    }
}