{
    "meta": {
        "symbol": "ORE",
        "name": "Galactrum",
        "supply": {
            "max": null
        },
        "web": {
            "websites": [
                "https:\/\/galactrum.org\/"
            ],
            "announcement": "https:\/\/bitcointalk.org\/index.php?topic=2576111.0",
            "source_code": "https:\/\/github.com\/galactrum\/galactrum",
            "explorers": [
                "https:\/\/explorer.galactrum.org"
            ],
            "coinmarketcap": "https:\/\/coinmarketcap.com\/currencies\/galactrum\/",
            "message_board": [],
            "chat": [
                "https:\/\/discord.gg\/zQcPK9G"
            ]
        },
        "original_codebase": "bitcoin"
    },
    "main": {
        "symbol": "ORE",
        "name": "Galactrum - Mainnet",
        "testnet": false,
        "port": 6270,
        "port_rpc": 6269,
        "protocol": {
            "magic": "0xb1ded0af"
        },
        "seeds_dns": [
            "seed1.galactrum.network",
            "seed2.galactrum.network",
            "seed3.galactrum.network",
            "seed4.galactrum.network",
            "seed5.galactrum.network"
        ],
        "prefixes": {
            "private": 204,
            "public": 38,
            "scripthash": 16,
            "bech32": null,
            "bip44": null,
            "extended": {
                "xpub": {
                    "public": "0x0488b21e",
                    "private": "0x0488ade4"
                },
                "ypub": {
                    "public": "0x049d7cb2",
                    "private": "0x049d7878",
                    "undefined_used_btc": true
                },
                "zpub": {
                    "public": "0x04b24746",
                    "private": "0x04b2430c",
                    "undefined_used_btc": true
                },
                "Ypub": {
                    "public": "0x0295b43f",
                    "private": "0x0295b005",
                    "undefined_used_btc": true
                },
                "Zpub": {
                    "public": "0x02aa7ed3",
                    "private": "0x02aa7a99",
                    "undefined_used_btc": true
                }
            }
        },
        "hash_genesis_block": "0000082da923a04678394f873852c7f08b777af30224b6e23296f586370e80ae",
        "message_magic": "\u0019DarkCoin Signed Message:\n",
        "decimals": 8
    },
    "test": {
        "symbol": "ORE",
        "name": "Galactrum - Testnet",
        "testnet": true,
        "port": 16270,
        "port_rpc": 16269,
        "protocol": {
            "magic": "0xb1ded0ab"
        },
        "seeds_dns": [
            "seed1.testnet.galactrum.network"
        ],
        "prefixes": {
            "private": 239,
            "public": 140,
            "scripthash": 19,
            "bech32": null,
            "bip44": 1,
            "extended": {
                "xpub": {
                    "public": "0x043587cf",
                    "private": "0x04358394"
                },
                "ypub": {
                    "public": "0x044a5262",
                    "private": "0x044a4e28",
                    "undefined_used_btc": true
                },
                "zpub": {
                    "public": "0x045f1cf6",
                    "private": "0x045f18bc",
                    "undefined_used_btc": true
                },
                "Zpub": {
                    "public": "0x02575483",
                    "private": "0x02575048",
                    "undefined_used_btc": true
                }
            }
        },
        "hash_genesis_block": "00000c0db74e7ed874ef2ad35c2401352326c1b4c58f5b7a5eaa2c22cac5c353",
        "message_magic": "\u0019DarkCoin Signed Message:\n",
        "decimals": 8
    },
    "regtest": {
        "symbol": "ORE",
        "name": "Galactrum - Regtest",
        "testnet": true,
        "port": 19994,
        "port_rpc": 18332,
        "protocol": {
            "magic": "0xfcc1b7dc"
        },
        "seeds_dns": [],
        "prefixes": {
            "private": 239,
            "public": 140,
            "scripthash": 19,
            "bech32": null,
            "bip44": 1,
            "extended": {
                "xpub": {
                    "public": "0x043587cf",
                    "private": "0x04358394"
                }
            }
        },
        "hash_genesis_block": "0x000008ca1832a4baf228eb1553c03d3a2c8e02399550dd6ea8d65cec3ef23d2e0xe0028eb9648db56b1ac77cf090b99048a8007e2bb64b68f092c03c7f56a662c7",
        "message_magic": "\u0019DarkCoin Signed Message:\n",
        "decimals": 8
    }
}